{"name":"build-javascript","namedChunkGroups":{"app":{"name":"app","assets":[{"name":"webpack-runtime-553319b1417c6371c9b1.js","size":4828},{"name":"framework-3325d8c9a53b9dbe3578.js","size":140831},{"name":"app-ed8fccc1dcf214eddb3c.js","size":61791}],"filteredAssets":0,"assetsSize":207450,"filteredAuxiliaryAssets":3,"auxiliaryAssetsSize":597672},"component---src-pages-404-js":{"name":"component---src-pages-404-js","assets":[{"name":"component---src-pages-404-js-e46958fe9b9db1dbc03f.js","size":832}],"filteredAssets":0,"assetsSize":832,"filteredAuxiliaryAssets":1,"auxiliaryAssetsSize":1773},"component---src-pages-index-js":{"name":"component---src-pages-index-js","assets":[{"name":"styles.3bcbe4b7436363f0cfae.css","size":48830},{"name":"component---src-pages-index-js-9b4bfbb3e29e5f992be5.js","size":13439}],"filteredAssets":0,"assetsSize":62269,"filteredAuxiliaryAssets":3,"auxiliaryAssetsSize":280122}},"assetsByChunkName":{"app":["webpack-runtime-553319b1417c6371c9b1.js","framework-3325d8c9a53b9dbe3578.js","app-ed8fccc1dcf214eddb3c.js"],"component---src-pages-404-js":["component---src-pages-404-js-e46958fe9b9db1dbc03f.js"],"component---src-pages-index-js":["styles.3bcbe4b7436363f0cfae.css","component---src-pages-index-js-9b4bfbb3e29e5f992be5.js"]},"childAssetsByChunkName":{}}